campman_observability/__init__.py
campman_observability/observability.py
campman_observability_lib_py-0.1.4.dist-info/licenses/LICENSE
campman_observability_lib_py-0.1.4.dist-info/METADATA
campman_observability_lib_py-0.1.4.dist-info/WHEEL
campman_observability_lib_py-0.1.4.dist-info/top_level.txt
campman_observability_lib_py-0.1.4.dist-info/RECORD
