Metadata-Version: 2.4
Name: campman-observability-lib-py
Version: 0.1.4
Summary: OpenTelemetry observability library for Flask applications with Google Cloud Platform integration
Author-email: Francesco Deleo <francesco.deleo@ingka.com>
License-Expression: MIT
Project-URL: Homepage, https://github.com/ingka-group-digital/campman-observability-lib-py
Project-URL: Repository, https://github.com/ingka-group-digital/campman-observability-lib-py
Project-URL: Issues, https://github.com/ingka-group-digital/campman-observability-lib-py/issues
Keywords: opentelemetry,observability,tracing,flask,gcp,google-cloud
Classifier: Development Status :: 4 - Beta
Classifier: Intended Audience :: Developers
Classifier: Operating System :: OS Independent
Classifier: Programming Language :: Python :: 3
Classifier: Programming Language :: Python :: 3.10
Classifier: Programming Language :: Python :: 3.11
Classifier: Programming Language :: Python :: 3.12
Classifier: Programming Language :: Python :: 3.13
Classifier: Topic :: Software Development :: Libraries :: Python Modules
Classifier: Topic :: System :: Monitoring
Classifier: Topic :: System :: Logging
Requires-Python: >=3.10
License-File: LICENSE
Requires-Dist: flask>=3.1.1
Requires-Dist: opentelemetry-api>=1.36.0
Requires-Dist: opentelemetry-sdk>=1.36.0
Requires-Dist: opentelemetry-instrumentation-flask>=0.57b0
Requires-Dist: opentelemetry-instrumentation-requests>=0.57b0
Requires-Dist: opentelemetry-exporter-gcp-trace>=1.9.0
Requires-Dist: opentelemetry-propagator-gcp>=1.9.0
Provides-Extra: dev
Requires-Dist: pytest>=6.0; extra == "dev"
Requires-Dist: pytest-cov>=2.0; extra == "dev"
Requires-Dist: black>=21.0; extra == "dev"
Requires-Dist: flake8>=3.8; extra == "dev"
Requires-Dist: mypy>=0.910; extra == "dev"
Dynamic: license-file
